Metadata-Version: 2.1
Name: pypotree
Version: 1.0.5
Summary: Potree visualization for jypyter notebooks
Home-page: https://github.com/cmla/pypotree
Author: Gabriele Facciolo
Author-email: gfacciol@gmail.com
License: UNKNOWN
Platform: UNKNOWN
Requires-Python: >=2.7
